mkmod.py
setup.py
mkmod.egg-info/PKG-INFO
mkmod.egg-info/SOURCES.txt
mkmod.egg-info/dependency_links.txt
mkmod.egg-info/entry_points.txt
mkmod.egg-info/top_level.txt