Metadata-Version: 1.0
Name: mkmod
Version: 0.1
Summary: Makes Python modules.
Home-page: http://github.com/nosamanuel/mkmod
Author: Noah Seger
Author-email: nosamanuel@gmail.com
License: MIT
Keywords: modules
Platform: UNKNOWN
Classifier: Development Status :: 4 - Beta
Classifier: Intended Audience :: Developers
Classifier: Topic :: Software Development :: Code Generators
Classifier: Programming Language :: Python :: 2.5
Classifier: Programming Language :: Python :: 2.6
Classifier: Programming Language :: Python :: 2.7
